astro_platform_api_client/__init__.py
astro_platform_api_client/api/__init__.py
astro_platform_api_client/api/alerts/__init__.py
astro_platform_api_client/api/alerts/create_alert.py
astro_platform_api_client/api/alerts/delete_alert.py
astro_platform_api_client/api/alerts/get_alert.py
astro_platform_api_client/api/alerts/list_alerts.py
astro_platform_api_client/api/alerts/update_alert.py
astro_platform_api_client/api/cluster/__init__.py
astro_platform_api_client/api/cluster/create_cluster.py
astro_platform_api_client/api/cluster/delete_cluster.py
astro_platform_api_client/api/cluster/get_cluster.py
astro_platform_api_client/api/cluster/list_clusters.py
astro_platform_api_client/api/cluster/update_cluster.py
astro_platform_api_client/api/deploy/__init__.py
astro_platform_api_client/api/deploy/create_deploy.py
astro_platform_api_client/api/deploy/deploy_rollback.py
astro_platform_api_client/api/deploy/finalize_deploy.py
astro_platform_api_client/api/deploy/get_deploy.py
astro_platform_api_client/api/deploy/list_deploys.py
astro_platform_api_client/api/deploy/update_deploy.py
astro_platform_api_client/api/deployment/__init__.py
astro_platform_api_client/api/deployment/create_deployment.py
astro_platform_api_client/api/deployment/delete_deployment.py
astro_platform_api_client/api/deployment/delete_deployment_hibernation_override.py
astro_platform_api_client/api/deployment/get_deployment.py
astro_platform_api_client/api/deployment/list_deployments.py
astro_platform_api_client/api/deployment/update_deployment.py
astro_platform_api_client/api/deployment/update_deployment_hibernation_override.py
astro_platform_api_client/api/environment/__init__.py
astro_platform_api_client/api/environment/create_environment_object.py
astro_platform_api_client/api/environment/delete_environment_object.py
astro_platform_api_client/api/environment/exclude_linking_environment_object.py
astro_platform_api_client/api/environment/get_environment_object.py
astro_platform_api-1.1.1.dist-info/METADATA
astro_platform_api-1.1.1.dist-info/WHEEL
astro_platform_api-1.1.1.dist-info/RECORD
